{
  "name": "Daniel Johnson",
  "email": "daniel.johnson.dev@outlook.com",
  "phone": "",
  "location": "Los Angeles, CA",
  "linkedin": "",
  "website": "",
  
  "experience": [
    {
      "company": "PROTEGRITY",
      "title": "Senior Software Engineer",
      "location": "",
      "start_date": "Feb 2023",
      "end_date": "Present"
    },
    {
      "company": "Comfy",
      "title": "Software Engineer",
      "location": "",
      "start_date": "Apr 2022",
      "end_date": "Jan 2023"
    },
    {
      "company": "INFINITY SYSTEMS ENGINEERING",
      "location": "",
      "start_date": "May 2021",
      "end_date": "Apr 2022"
    },
    {
      "company": "Aerodyne Industries LLC",
      "location": "",
      "start_date": "Mar 2019",
      "end_date": "Jan 2022"
    }
  ],
  
  "education": [
    {
      "degree": "Master of Science in Computer Science",
      "school": "Georgia Institute of Technology",
      "start_year": "Sep 2020",
      "end_year": "Sep 2021"
    },
    {
      "degree": "Computer Engineering",
      "school": "Drexel University",
      "start_year": "Sep 2014",
      "end_year": "Jun 2019"
    },
    {
      "degree": "Study abroad - Bachelors of Science in Computer Engineering - Minor in Electrical ",
      "school": "Shanghai Jiao Tong University",
      "start_year": "Jul 2017",
      "end_year": "Jan 2018"
    }
  ]
}
